src/__init__.py
src/qab.py
qab-0.1.0.dist-info/LICENSE
qab-0.1.0.dist-info/METADATA
qab-0.1.0.dist-info/WHEEL
qab-0.1.0.dist-info/top_level.txt
qab-0.1.0.dist-info/RECORD
