Metadata-Version: 2.1
Name: qab
Version: 0.1.0
Summary: low-code quality assurance bot framework
Author: joman2
License: MIT
Project-URL: Source Repository, https://github.com/joman2/qab/
License-File: LICENSE
Requires-Dist: uiautomator2
